{
  "logs": [
    {
      "id": 3,
      "message": "hard drive failed on 321",
      "attention": false,
      "tech": "John Doe",
      "date": "2021-07-21T05:40:43.727Z"
    },
    {
      "message": "something stinky downstairs",
      "attention": true,
      "tech": "John Doe",
      "date": "2021-07-21T04:57:33.237Z",
      "id": 4
    }
  ],
  "techs": [
    {
      "id": 1,
      "firstName": "John",
      "lastName": "Doe"
    },
    {
      "id": 2,
      "firstName": "Sam",
      "lastName": "Smith"
    },
    {
      "id": 3,
      "firstName": "Sara",
      "lastName": "Wilson"
    },
    {
      "firstName": "val",
      "lastName": "khut",
      "id": 4
    }
  ]
}